loginserviceanfia/__init__.py
loginserviceanfia/loginserviceanfia.py
loginserviceanfia-0.1.6.dist-info/METADATA
loginserviceanfia-0.1.6.dist-info/WHEEL
loginserviceanfia-0.1.6.dist-info/RECORD
