Metadata-Version: 2.3
Name: loginserviceanfia
Version: 0.1.6
Summary: Project developed to handle passwords, APIs and servers for internal ANFIA use.
Author: Cosimo Di Martino
Author-email: derto.dimartino@proton.me
Requires-Python: >=3.8
Classifier: Programming Language :: Python :: 3
Classifier: Programming Language :: Python :: 3.8
Classifier: Programming Language :: Python :: 3.9
Classifier: Programming Language :: Python :: 3.10
Classifier: Programming Language :: Python :: 3.11
Classifier: Programming Language :: Python :: 3.12
Classifier: Programming Language :: Python :: 3.13
Requires-Dist: pywinauto (>=0.6.9,<0.7.0)
Requires-Dist: spyder-kernels (>=3.0.0,<3.1.0)
Requires-Dist: urllib3 (>=1.26.5)
